telegram_core/__init__.py
telegram_core-1.0.0.dist-info/licenses/LICENSE
telegram_core-1.0.0.dist-info/METADATA
telegram_core-1.0.0.dist-info/WHEEL
telegram_core-1.0.0.dist-info/top_level.txt
telegram_core-1.0.0.dist-info/RECORD
