Metadata-Version: 2.4
Name: telegram_core
Version: 1.0.0
Summary: The modern MTProto wrapper and Telegram user API client
Author-email: nsdkinx <nsdkinx@ya.ru>
License:                     GNU GENERAL PUBLIC LICENSE
Project-URL: Homepage, https://github.com/miraclebots-dev/telegram-core
Keywords: telegram,telegram-api,mtproto
Classifier: Programming Language :: Python
Classifier: Programming Language :: Python :: 3
Requires-Python: >=3.9
License-File: LICENSE
Dynamic: license-file
